{
  "hash": "3285261f",
  "browserHash": "15f91285",
  "optimized": {
    "react": {
      "src": "../../react/index.js",
      "file": "react.js",
      "fileHash": "a9eb65a5",
      "needsInterop": true
    },
    "react/jsx-dev-runtime": {
      "src": "../../react/jsx-dev-runtime.js",
      "file": "react_jsx-dev-runtime.js",
      "fileHash": "124605fe",
      "needsInterop": true
    },
    "react-dom/client": {
      "src": "../../react-dom/client.js",
      "file": "react-dom_client.js",
      "fileHash": "db896fe9",
      "needsInterop": true
    }
  },
  "chunks": {
    "chunk-UZX524IT": {
      "file": "chunk-UZX524IT.js"
    }
  }
}